README.md
setup.py
cprint/__init__.py
cprint/cprint.py
cprint.egg-info/PKG-INFO
cprint.egg-info/SOURCES.txt
cprint.egg-info/dependency_links.txt
cprint.egg-info/top_level.txt