Metadata-Version: 2.1
Name: cprint
Version: 1.2.2
Summary: Printing and debugging with color
Home-page: https://github.com/EVasseure/cprint
Author: Erwan Vasseure
Author-email: e.vasseure@gmail.com
License: MIT
Platform: UNKNOWN
